azure/onlineexperimentation/__init__.py
azure/onlineexperimentation/_client.py
azure/onlineexperimentation/_configuration.py
azure/onlineexperimentation/_model_base.py
azure/onlineexperimentation/_patch.py
azure/onlineexperimentation/_serialization.py
azure/onlineexperimentation/_vendor.py
azure/onlineexperimentation/_version.py
azure/onlineexperimentation/py.typed
azure/onlineexperimentation/_operations/__init__.py
azure/onlineexperimentation/_operations/_operations.py
azure/onlineexperimentation/_operations/_patch.py
azure/onlineexperimentation/_utils/__init__.py
azure/onlineexperimentation/_utils/model_base.py
azure/onlineexperimentation/_utils/serialization.py
azure/onlineexperimentation/_utils/utils.py
azure/onlineexperimentation/aio/__init__.py
azure/onlineexperimentation/aio/_client.py
azure/onlineexperimentation/aio/_configuration.py
azure/onlineexperimentation/aio/_patch.py
azure/onlineexperimentation/aio/_vendor.py
azure/onlineexperimentation/aio/_operations/__init__.py
azure/onlineexperimentation/aio/_operations/_operations.py
azure/onlineexperimentation/aio/_operations/_patch.py
azure/onlineexperimentation/models/__init__.py
azure/onlineexperimentation/models/_enums.py
azure/onlineexperimentation/models/_models.py
azure/onlineexperimentation/models/_patch.py
azure_onlineexperimentation-1.0.0b1.dist-info/LICENSE
azure_onlineexperimentation-1.0.0b1.dist-info/METADATA
azure_onlineexperimentation-1.0.0b1.dist-info/WHEEL
azure_onlineexperimentation-1.0.0b1.dist-info/top_level.txt
azure_onlineexperimentation-1.0.0b1.dist-info/RECORD
